datacraft/__init__.py
datacraft/__main__.py
datacraft/builder.py
datacraft/casters.py
datacraft/cli.py
datacraft/defaults.py
datacraft/distributions.py
datacraft/entrypoints.py
datacraft/exceptions.py
datacraft/infer.py
datacraft/loader.py
datacraft/logging_handler.py
datacraft/outputs.py
datacraft/preprocessor.py
datacraft/py.typed
datacraft/registries.py
datacraft/schemas.py
datacraft/server.py
datacraft/spec_formatters.py
datacraft/suppliers.py
datacraft/template_engines.py
datacraft/usage.py
datacraft/utils.py
datacraft/_infer/__init__.py
datacraft/_infer/__main__.py
datacraft/_infer/date_str_analyzers.py
datacraft/_infer/default_analyzer.py
datacraft/_infer/entrypoint.py
datacraft/_infer/geo_analyzers.py
datacraft/_infer/helpers.py
datacraft/_infer/network_str_analyzers.py
datacraft/_infer/num_analyzers.py
datacraft/_infer/regex_str_analyzers.py
datacraft/_infer/str_analyzers.py
datacraft/_registered_types/__init__.py
datacraft/_registered_types/calculate.py
datacraft/_registered_types/char_class.py
datacraft/_registered_types/combine.py
datacraft/_registered_types/common.py
datacraft/_registered_types/config_ref.py
datacraft/_registered_types/csv.py
datacraft/_registered_types/date.py
datacraft/_registered_types/distribution.py
datacraft/_registered_types/entrypoint.py
datacraft/_registered_types/geo.py
datacraft/_registered_types/iteration.py
datacraft/_registered_types/nested.py
datacraft/_registered_types/network.py
datacraft/_registered_types/numeric_types.py
datacraft/_registered_types/ref_list.py
datacraft/_registered_types/refs.py
datacraft/_registered_types/replace.py
datacraft/_registered_types/sample.py
datacraft/_registered_types/schemas.py
datacraft/_registered_types/templated.py
datacraft/_registered_types/unicode_range.py
datacraft/_registered_types/uuid_handler.py
datacraft/_registered_types/values.py
datacraft/_registered_types/schema/__init__.py
datacraft/_registered_types/schema/calculate.schema.json
datacraft-0.12.1.dist-info/licenses/LICENSE.txt
datacraft-0.12.1.dist-info/METADATA
datacraft-0.12.1.dist-info/WHEEL
datacraft-0.12.1.dist-info/entry_points.txt
datacraft-0.12.1.dist-info/top_level.txt
datacraft-0.12.1.dist-info/RECORD
