Metadata-Version: 2.4
Name: datacraft
Version: 0.12.1
Summary: Data Generation Through Specification
Home-page: https://github.com/bbux-dev/datacraft
Author: Brian Buxton
Author-email: bbux.dev@gmail.com
License: MIT
Classifier: Development Status :: 3 - Alpha
Classifier: Intended Audience :: Developers
Classifier: Topic :: Software Development :: Build Tools
Classifier: License :: OSI Approved :: BSD License
Classifier: Programming Language :: Python :: 3.10
Classifier: Programming Language :: Python :: 3.11
Classifier: Programming Language :: Python :: 3.12
License-File: LICENSE.txt
Requires-Dist: setuptools
Requires-Dist: pyyaml>=5.1
Requires-Dist: catalogue>=2.0.1
Requires-Dist: jinja2>=3.0.3
Requires-Dist: jsonschema>=3.2.0
Requires-Dist: asteval>=0.9.25
Requires-Dist: importlib-resources>=5.2.2
Requires-Dist: importlib-metadata>=4.8.2
Provides-Extra: test
Requires-Dist: pytest>=6.2.2; extra == "test"
Requires-Dist: pycodestyle; extra == "test"
Requires-Dist: pytest-cov; extra == "test"
Requires-Dist: pytest-mock; extra == "test"
Requires-Dist: pandas; extra == "test"
Requires-Dist: flask; extra == "test"
Provides-Extra: all
Requires-Dist: pytest>=6.2.2; extra == "all"
Requires-Dist: pycodestyle; extra == "all"
Requires-Dist: pytest-cov; extra == "all"
Requires-Dist: pytest-mock; extra == "all"
Requires-Dist: pandas; extra == "all"
Requires-Dist: flask; extra == "all"
Dynamic: license-file
